[
    {
        "word": "كتاب",
        "clue": "مجموعة من الصفحات تحتوي على معلومات أو قصة.",
        "direction": "across",
        "row": 0,
        "col": 0
    },
    {
        "word": "مدرسة",
        "clue": "مؤسسة تعليمية يتعلم فيها الطلاب.",
        "direction": "down",
        "row": 0,
        "col": 0
    },
    {
        "word": "قلم",
        "clue": "أداة تستخدم للكتابة.",
        "direction": "down",
        "row": 0,
        "col": 3
    },
    {
        "word": "ماء",
        "clue": "سائل شفاف لا طعم له ويشربه الإنسان.",
        "direction": "across",
        "row": 2,
        "col": 0
    },
    {
        "word": "شمس",
        "clue": "النجمة التي تضئ نهار الأرض.",
        "direction": "down",
        "row": 0,
        "col": 5
    },
    {
        "word": "قلب",
        "clue": "عضو يضخ الدم في الجسم.",
        "direction": "across",
        "row": 4,
        "col": 0
    },
    {
        "word": "نهر",
        "clue": "مسار مائي كبير يتدفق نحو البحر.",
        "direction": "down",
        "row": 2,
        "col": 4
    },
    {
        "word": "طائرة",
        "clue": "وسيلة نقل جوية تطير في السماء.",
        "direction": "across",
        "row": 6,
        "col": 2
    },
    {
        "word": "قمر",
        "clue": "النجمة التي تضيء ليلاً.",
        "direction": "down",
        "row": 2,
        "col": 7
    },
    {
        "word": "حديقة",
        "clue": "مكان يحتوي على نباتات وزهور.",
        "direction": "across",
        "row": 8,
        "col": 0
    },
    {
        "word": "سمك",
        "clue": "كائن حي يعيش في الماء ويتنفس بالخياشيم.",
        "direction": "down",
        "row": 0,
        "col": 9
    },
    {
        "word": "زهرة",
        "clue": "جزء من النبات يتفتح ويعطي رائحة جميلة.",
        "direction": "across",
        "row": 9,
        "col": 0
    },
    {
        "word": "طاولة",
        "clue": "أثاث يستخدم لوضع الأشياء عليه.",
        "direction": "down",
        "row": 4,
        "col": 5
    },
    {
        "word": "بحر",
        "clue": "مسطح مائي مالح واسع.",
        "direction": "across",
        "row": 5,
        "col": 0
    },
    {
        "word": "مدينة",
        "clue": "مكان كبير يقطنه الكثير من الناس.",
        "direction": "down",
        "row": 6,
        "col": 0
    },
    {
        "word": "شجرة",
        "clue": "نبات طويل ذو فروع وأوراق.",
        "direction": "across",
        "row": 7,
        "col": 3
    },
    {
        "word": "مدينة",
        "clue": "مكان كبير يقطنه الكثير من الناس.",
        "direction": "down",
        "row": 6,
        "col": 0
    },
    {
        "word": "سماء",
        "clue": "الفضاء الذي يحيط بالأرض ويرى فيه السحاب والنجوم.",
        "direction": "across",
        "row": 3,
        "col": 2
    },
    {
        "word": "بحر",
        "clue": "مسطح مائي مالح واسع.",
        "direction": "down",
        "row": 5,
        "col": 0
    },
    {
        "word": "ريح",
        "clue": "حركة الهواء التي نشعر بها.",
        "direction": "across",
        "row": 1,
        "col": 5
    },
    {
        "word": "نجم",
        "clue": "جسم سماوي يضيء في الليل.",
        "direction": "down",
        "row": 3,
        "col": 6
    }
]
